top_ten_bot/__init__.py
top_ten_bot/main/__init__.py
top_ten_bot/main/create_top_ten.py
top_ten_bot/main/encode_video.py
top_ten_bot/main/image_search.py
top_ten_bot/main/music_search.py
top_ten_bot/test/__init__.py
top_ten_bot/test/all_tests.py
top_ten_bot/test/test_create_top_ten.py
top_ten_bot/test/test_encode_video.py
top_ten_bot/test/test_image_search.py
top_ten_bot/test/test_music_search.py
TopTenBot-0.4.0.dist-info/LICENSE
TopTenBot-0.4.0.dist-info/METADATA
TopTenBot-0.4.0.dist-info/WHEEL
TopTenBot-0.4.0.dist-info/entry_points.txt
TopTenBot-0.4.0.dist-info/top_level.txt
TopTenBot-0.4.0.dist-info/RECORD
