Metadata-Version: 2.1
Name: TopTenBot
Version: 0.4.0
Summary: Utility for creating top 10 videos
Home-page: https://github.com/Drakovek/TopTenBot
Author: Drakovek
Author-email: DrakovekMail@gmail.com
License: UNKNOWN
Platform: UNKNOWN
Classifier: Programming Language :: Python :: 3
Classifier: License :: OSI Approved :: GNU General Public License v3 (GPLv3)
Classifier: Operating System :: OS Independent
Requires-Python: >=3.0
License-File: LICENSE
Requires-Dist: dvk-archive
Requires-Dist: moviepy
Requires-Dist: pillow
Requires-Dist: youtube-dl
Requires-Dist: youtube-search-python
